Metadata-Version: 2.1
Name: seg
Version: 0.0.1
Summary: Image segmentation tools specially for blood vessels.
Home-page: http://pypi.python.org/pypi/seg/
Author: Yinsheng Zhang (Ph.D.)
Author-email: oo@zju.edu.cn
License: LICENSE.txt
License-File: LICENCE
Requires-Dist: flask
Requires-Dist: scikit-learn
Requires-Dist: matplotlib
Requires-Dist: numpy
Requires-Dist: pandas
Requires-Dist: statsmodels
Requires-Dist: h5py
Requires-Dist: opencv-python
Requires-Dist: torch
